LICENSE
MANIFEST.in
README.md
setup.py
clickzetta_travel.egg-info/PKG-INFO
clickzetta_travel.egg-info/SOURCES.txt
clickzetta_travel.egg-info/dependency_links.txt
clickzetta_travel.egg-info/entry_points.txt
clickzetta_travel.egg-info/not-zip-safe
clickzetta_travel.egg-info/requires.txt
clickzetta_travel.egg-info/top_level.txt
travel/__init__.py
travel/version.py
travel/batch/__init__.py
travel/batch/trans_batch.py
travel/glot/__init__.py
travel/glot/glot.py
travel/streamlit/__init__.py
travel/streamlit/conf_cz.template
travel/streamlit/conf_mysql.template
travel/streamlit/icon.png
travel/streamlit/main.py
travel/streamlit/run.sh
travel/streamlit/conf/clickzetta.json
travel/streamlit/conf/mysql.json
travel/streamlit/conf/pg.json
travel/streamlit/pages/1_unify.py
travel/streamlit/pages/2_ast_viewer.py
travel/streamlit/pages/__init__.py
travel/test/__init__.py
travel/test/batch_check.py
travel/test/data_diff_util.py
travel/test/feishu_warning.py
travel/test/full_table_validation.py
travel/test/schema_check.py
travel/test/sqlite3_add_cols.py
travel/test/validation_page.py
travel/test/xsy_batch_check.py
travel/test/xsy_repeat_id_check.py
travel/util/__init__.py
travel/util/config.py
travel/util/connect_util.py
travel/util/util.py
travel/util/validation_util.py
travel/validation/__init__.py
travel/validation/check_unify.py
travel/validation/cz_conf_example.json
travel/validation/global_conf.json
travel/validation/mysql_conf_example.json
travel/validation/pg_conf_example.json
travel/validation/run.sh
travel/validation/view/__init__.py
travel/validation/view/main.py
travel/validation/view/pages/XSY_Full_Table_Check.py
travel/validation/view/pages/XSY_Schema_Validation_Overview.py
travel/validation/view/pages/XSY_Validation_Overview.py
travel/validation/view/pages/__init__.py