Metadata-Version: 2.1
Name: clickzetta-travel
Version: 0.0.7.3
Summary: Toolkits including Transpile, Run, And Validate queries, for Evaluating clickzetta with Love.
Home-page: https://www.yunqi.tech/
Author: mocun
Author-email: hanmiao.li@clickzetta.com
Platform: Posix; MacOS X;
Requires-Python: >=3.7
Provides-Extra: all
License-File: LICENSE
